[{"firstname":"Thomas","career":[{"start":"2022-09-01","end":null,"team":{"name":"Bochum","logo":"https://media.api-sports.io/football/teams/176.png","id":176}},{"start":"2020-07-01","end":"2022-09-01","team":{"name":"Vitesse","logo":"https://media.api-sports.io/football/teams/200.png","id":200}},{"start":"2018-02-01","end":"2019-03-01","team":{"name":"Austria Vienna","logo":"https://media.api-sports.io/football/teams/601.png","id":601}},{"start":"2017-06-01","end":"2017-08-01","team":{"name":"Erzgebirge Aue","logo":"https://media.api-sports.io/football/teams/190.png","id":190}},{"start":"2016-02-01","end":"2016-06-01","team":{"name":"Salzburg U19","logo":"https://media.api-sports.io/football/teams/7928.png","id":7928}},{"start":"2015-12-01","end":"2015-12-01","team":{"name":"Salzburg","logo":"https://media.api-sports.io/football/teams/571.png","id":571}},{"start":"2015-09-01","end":"2015-12-01","team":{"name":"Salzburg U19","logo":"https://media.api-sports.io/football/teams/7928.png","id":7928}},{"start":"2015-06-01","end":"2017-06-01","team":{"name":"Liefering","logo":"https://media.api-sports.io/football/teams/1400.png","id":1400}}],"nationality":"Germany","name":"T. Letsch","birth":{"date":"1968-08-26","country":"Germany","place":null},"weight":null,"photo":"https://media.api-sports.io/football/coachs/2935.png","id":2935,"team":{"name":"Bochum","logo":"https://media.api-sports.io/football/teams/176.png","id":176},"age":56,"lastname":"Letsch","height":null},{"firstname":"Heiko","career":[{"start":"2022-09-01","end":"2022-09-01","team":{"name":"Bochum","logo":"https://media.api-sports.io/football/teams/176.png","id":176}},{"start":"2020-07-01","end":null,"team":{"name":"Bochum U19","logo":"https://media.api-sports.io/football/teams/10248.png","id":10248}},{"start":"2018-02-01","end":"2018-02-01","team":{"name":"Bochum","logo":"https://media.api-sports.io/football/teams/176.png","id":176}}],"nationality":"Germany","name":"H. Butscher","birth":{"date":"1980-07-28","country":"Germany","place":"Leutkirch"},"weight":"86 kg","photo":"https://media.api-sports.io/football/coachs/10299.png","id":10299,"team":{"name":"Bochum","logo":"https://media.api-sports.io/football/teams/176.png","id":176},"age":44,"lastname":"Butscher","height":"189 cm"}]